{
  "properties": {
    "connectionParameters": {
      "token": {
        "type": "oauthSetting",
        "oAuthSettings": {
          "identityProvider": "oauth2",
          "clientId": "[[DUMMY]]",
          "scopes": [
            "robots task-files task-schedules"
          ],
          "redirectMode": "Global",
          "redirectUrl": "https://global.consent.azure-apim.net/redirect",
          "properties": {
            "IsFirstParty": "False",
            "IsOnbehalfofLoginSupported": false
          },
          "customParameters": {
            "authorizationUrl": {
              "value": "https://api.yarado.com/oauth/authorize"
            },
            "tokenUrl": {
              "value": "https://api.yarado.com/oauth/token"
            },
            "refreshUrl": {
              "value": "https://api.yarado.com/oauth/refresh"
            }
          }
        }
      }
    },
    "iconBrandColor": "#f8aaaa",
    "capabilities": [],
    "publisher": "Yarado",
    "stackOwner": "Yarado"
  }
}