{
  "properties": {
    "connectionParameters": {
      "api_key": {
        "type": "securestring",
        "uiDefinition": {
          "displayName": "CSI API Key",
          "description": "Please enter your CSI API Key, found in the CSI Cloud Dashboard.",
          "tooltip": "If you need an API Key or are experiencing issues, please contact CSI Support (www.csiinc.com/support).",
          "constraints": {
            "tabIndex": 2,
            "clearText": false,
            "required": "true"
          }
        }
      }
    },
    "iconBrandColor": "#00A9E0",
    "capabilities": [],
    "publisher": "Computer System Innovations, Inc.",
    "stackOwner": "Advanced Solutions International, Inc."
  }
}
