{
  "properties": {
    "capabilities": [],
    "connectionParameters": {
      "token": {
        "oAuthSettings": {
          "clientId": "xxxxxxxxxxxxxxxxxxxxxxxx",
          "customParameters": {
            "authorizationUrl": {
              "value": "https://auth.pdf4me.com/connect/authorize"
            },
            "refreshUrl": {
              "value": "https://auth.pdf4me.com/connect/token"
            },
            "tokenUrl": {
              "value": "https://auth.pdf4me.com/connect/token"
            }
          },
          "identityProvider": "oauth2",
          "properties": {
            "IsFirstParty": "False"
          },
          "redirectMode": "Global",
          "redirectUrl": "https://global.consent.azure-apim.net/redirect",
          "scopes": [
            "openid",
            "profile",
            "email",
            "offline_access"
          ]
        },
        "type": "oauthSetting"
      }
    },
    "iconBrandColor": "#EEEEEE",
    "publisher": "Ynoox",
    "stackOwner": "PDF4me"
  }
}